{
  "url_date": "2026-06-04",
  "weekday": "Thursday",
  "filing_dates": [
    "2026-06-03"
  ],
  "generated_at": "2026-06-04T10:41:49+00:00",
  "tickers": [
    {
      "ticker": "LODE",
      "name": "Comstock Inc.",
      "total_value": 3087170.3812,
      "ev_basic": 244611494.07170868,
      "mc_basic": 297579295.0717087,
      "insiders": [
        {
          "reporter_name": "Pei Steven Yu-Tsung",
          "relationship": "Director",
          "total_value": 2893354.9812000003,
          "shares": 720000.0,
          "txn_count": 6
        },
        {
          "reporter_name": "SPENCE ROBERT",
          "relationship": "Director",
          "total_value": 193815.40000000002,
          "shares": 48820.0,
          "txn_count": 2
        }
      ]
    },
    {
      "ticker": "PRTA",
      "name": "PROTHENA CORP PUBLIC LTD CO",
      "total_value": 942600.0,
      "ev_basic": 137528878.034235,
      "mc_basic": 466990878.034235,
      "insiders": [
        {
          "reporter_name": "SCULLY WILLIAM P",
          "relationship": "10% Owner",
          "total_value": 942600.0,
          "shares": 100000.0,
          "txn_count": 2
        }
      ]
    },
    {
      "ticker": "LEE",
      "name": "LEE ENTERPRISES, Inc",
      "total_value": 781872.0,
      "ev_basic": 690332418.8160095,
      "mc_basic": 237193418.81600952,
      "insiders": [
        {
          "reporter_name": "Hoffmann David Henry",
          "relationship": "Director, 10% Owner",
          "total_value": 781872.0,
          "shares": 72800.0,
          "txn_count": 4
        }
      ]
    },
    {
      "ticker": "WOK",
      "name": "WORK Medical Technology Group LTD",
      "total_value": 757987.6320000001,
      "ev_basic": 3864085.8053067178,
      "mc_basic": 1561337.8053067178,
      "insiders": [
        {
          "reporter_name": "HRT FINANCIAL LP",
          "relationship": "10% Owner",
          "total_value": 757987.6320000001,
          "shares": 5492664.0,
          "txn_count": 2
        }
      ]
    },
    {
      "ticker": "BZUN",
      "name": "Baozun Inc.",
      "total_value": 216400.0,
      "ev_basic": 498490351.14106965,
      "mc_basic": 455528351.14106965,
      "insiders": [
        {
          "reporter_name": "Qiu Wenbin",
          "relationship": "Director, Officer (Chief Executive Officer)",
          "total_value": 108400.0,
          "shares": 40000.0,
          "txn_count": 4
        },
        {
          "reporter_name": "Wu Junhua",
          "relationship": "Director, Officer (Chief Strategy Officer)",
          "total_value": 108000.0,
          "shares": 40000.0,
          "txn_count": 2
        }
      ]
    },
    {
      "ticker": "RCEL",
      "name": "AVITA Medical, Inc.",
      "total_value": 169873.0,
      "ev_basic": 165861021.54384995,
      "mc_basic": 128031021.54384995,
      "insiders": [
        {
          "reporter_name": "Woody Joseph Fralin",
          "relationship": "Director",
          "total_value": 169873.0,
          "shares": 40000.0,
          "txn_count": 8
        }
      ]
    },
    {
      "ticker": "EDBL",
      "name": "Edible Garden AG Inc",
      "total_value": 121500.0,
      "ev_basic": 1542801.4664675891,
      "mc_basic": 1104801.4664675891,
      "insiders": [
        {
          "reporter_name": "Wolinsky Scott",
          "relationship": "10% Owner",
          "total_value": 121500.0,
          "shares": 450000.0,
          "txn_count": 3
        }
      ]
    }
  ]
}